README.md
setup.cfg
setup.py
mbapi/__init__.py
mbapi/api.py
mbapi/labels.py
mbapi/tapi.py
mbapi.egg-info/PKG-INFO
mbapi.egg-info/SOURCES.txt
mbapi.egg-info/dependency_links.txt
mbapi.egg-info/top_level.txt