Metadata-Version: 1.1
Name: mbapi
Version: 1.2
Summary: A Python 3 API interface for Mercado Bitcoin's API.
Home-page: https://github.com/btrevizan/mb_api
Author: Bernardo Trevizan
Author-email: trevizanbernardo@gmail.com
License: UNKNOWN
Download-URL: https://github.com/btrevizan/mb_api/dist/mbapi-1.2.tar.gz
Keywords: bitcoin,api,mercado_bitcoin
Platform: UNKNOWN
